README.md
pyproject.toml
setup.cfg
setup.py
seres_client/__init__.py
seres_client/api_client.py
seres_client/api_response.py
seres_client/configuration.py
seres_client/exceptions.py
seres_client/rest.py
seres_client.egg-info/PKG-INFO
seres_client.egg-info/SOURCES.txt
seres_client.egg-info/dependency_links.txt
seres_client.egg-info/requires.txt
seres_client.egg-info/top_level.txt
seres_client/api/__init__.py
seres_client/api/access_keys_api.py
seres_client/api/authentication_api.py
seres_client/api/available_resource_assemblies_api.py
seres_client/api/flight_plan_creation_requests_api.py
seres_client/api/flight_plan_leg_resources_api.py
seres_client/api/flight_plan_legs_api.py
seres_client/api/flight_plan_references_api.py
seres_client/api/flight_plan_waypoints_api.py
seres_client/api/flight_plans_api.py
seres_client/api/future_activities_api.py
seres_client/api/futures_api.py
seres_client/api/mission_template_legs_api.py
seres_client/api/mission_template_waypoints_api.py
seres_client/api/mission_templates_api.py
seres_client/api/pad_windows_api.py
seres_client/api/ports_api.py
seres_client/api/resource_assembly_schema_energy_bank_components_api.py
seres_client/api/resource_assembly_schema_energy_bank_consumers_api.py
seres_client/api/resource_assembly_schema_energy_banks_api.py
seres_client/api/resource_assembly_schema_refuel_swaps_api.py
seres_client/api/resource_assembly_schemas_api.py
seres_client/api/resource_schema_action_schemas_api.py
seres_client/api/resource_schema_actions_api.py
seres_client/api/resource_schemas_api.py
seres_client/api/resources_api.py
seres_client/api/subnets_api.py
seres_client/api/users_api.py
seres_client/models/__init__.py
seres_client/models/access_key_creation_schema.py
seres_client/models/access_key_schema.py
seres_client/models/access_key_status_enum.py
seres_client/models/altitude.py
seres_client/models/app_missions_plans_schemas_mission_plan_waypoint_schema_waypoint_coordinate_schema_input.py
seres_client/models/app_missions_plans_schemas_mission_plan_waypoint_schema_waypoint_coordinate_schema_output.py
