Metadata-Version: 2.1
Name: seres-client
Version: 0.0.30
Summary: Secore API
Home-page: UNKNOWN
Author: OpenAPI Generator community
Author-email: team@openapitools.org
License: UNKNOWN
Keywords: OpenAPI,OpenAPI-Generator,Secore API
Platform: UNKNOWN
